mistune_jira/__init__.py
mistune_jira/jiraRenderer.py
mistune_jira-2023.12.6.0.dist-info/LICENSE
mistune_jira-2023.12.6.0.dist-info/METADATA
mistune_jira-2023.12.6.0.dist-info/WHEEL
mistune_jira-2023.12.6.0.dist-info/top_level.txt
mistune_jira-2023.12.6.0.dist-info/RECORD
