Metadata-Version: 2.1
Name: mistune-jira
Version: 2023.12.6.0
Summary: A mostly functional plugin for mistune to render Jira's markup language
Author-email: Chris Halbersma <chris@halbersma.us>
License: BSD-3-Clause
Keywords: mistune,jira,atlassian
Classifier: Programming Language :: Python :: 3
Requires-Python: >=3.10
License-File: LICENSE
Requires-Dist: mistune
